hugo_unifier/__init__.py
hugo_unifier/apply_changes.py
hugo_unifier/create_graph.py
hugo_unifier/get_changes.py
hugo_unifier/graph_manipulations.py
hugo_unifier/hugo_fetch.py
hugo_unifier/main.py
hugo_unifier/orchestrated_fetch.py
hugo_unifier/plot_subgraph.py
hugo_unifier/symbol_manipulations.py
hugo_unifier-0.3.1.dist-info/METADATA
hugo_unifier-0.3.1.dist-info/WHEEL
hugo_unifier-0.3.1.dist-info/entry_points.txt
hugo_unifier-0.3.1.dist-info/RECORD
