Metadata-Version: 2.4
Name: hugo-unifier
Version: 0.3.1
Summary: Python package that can unify gene symbols across datasets based on the HUGO database.
Author-email: Nico Trummer <nictru32@gmail.com>
Classifier: Programming Language :: Python :: 3
Classifier: Programming Language :: Python :: 3.10
Classifier: Programming Language :: Python :: 3.11
Classifier: Programming Language :: Python :: 3.12
Classifier: Programming Language :: Python :: 3.13
Classifier: Programming Language :: Python :: 3.14
Requires-Python: >=3.10
Requires-Dist: anndata>=0.11.4
Requires-Dist: networkx>=3.4.2
Requires-Dist: requests>=2.32.3
Requires-Dist: rich-click>=1.8.8
